countloc/__init__.py
countloc/__main__.py
countloc-1.3.dist-info/LICENSE
countloc-1.3.dist-info/METADATA
countloc-1.3.dist-info/WHEEL
countloc-1.3.dist-info/entry_points.txt
countloc-1.3.dist-info/top_level.txt
countloc-1.3.dist-info/RECORD
