Metadata-Version: 2.1
Name: countloc
Version: 1.3
Summary: countloc is a simple CLI to count the number of lines of code in your directory that you wrote.
Home-page: UNKNOWN
Author: Anish Lakkapragada
Author-email: anish.lakkapragada@gmail.com
License: MIT
Keywords: LOC,SLOC,CLI
Platform: UNKNOWN
License-File: LICENSE
